personal_data_validator/__init__.py
personal_data_validator/main.py
personal_data_validator/setup.py
personal_data_validator/validator.py
data_validator_baliqees-0.1.0.dist-info/METADATA
data_validator_baliqees-0.1.0.dist-info/WHEEL
data_validator_baliqees-0.1.0.dist-info/top_level.txt
data_validator_baliqees-0.1.0.dist-info/RECORD
