Metadata-Version: 2.2
Name: data-validator-baliqees
Version: 0.1.0
Summary: A simple data validator for phone numbers, dates, and URLs.
Author-email: Baliqees Oladunjoye <baliqees.oladunjoye@gmail.com>
License: MIT
Project-URL: Homepage, https://github.com/Data-Epic/data-validator-Baliqees-Oladunjoye
Project-URL: Repository, https://github.com/Data-Epic/data-validator-Baliqees-Oladunjoye
Project-URL: Issues, https://github.com/Data-Epic/data-validator-Baliqees-Oladunjoye/issues
Requires-Python: >=3.7
Requires-Dist: pytest
